kahoot/__init__.py
kahoot/src/Assets.py
kahoot/src/ChallengeHandler.py
kahoot/src/WSHandler.py
kahoot/src/__init__.py
kahoot/src/consts.py
kahoot/src/token.py
KahootPY-0.1.4.dist-info/LICENSE
KahootPY-0.1.4.dist-info/METADATA
KahootPY-0.1.4.dist-info/WHEEL
KahootPY-0.1.4.dist-info/top_level.txt
KahootPY-0.1.4.dist-info/RECORD
